uuid25/__init__.py
uuid25-0.1.3.dist-info/LICENSE
uuid25-0.1.3.dist-info/METADATA
uuid25-0.1.3.dist-info/WHEEL
uuid25-0.1.3.dist-info/RECORD
