Metadata-Version: 2.1
Name: uuid25
Version: 0.1.3
Summary: 25-digit case-insensitive UUID encoding
Home-page: https://github.com/uuid25/python
License: Apache-2.0
Author: LiosK
Author-email: contact@mail.liosk.net
Requires-Python: >=3.8,<4.0
Classifier: License :: OSI Approved :: Apache Software License
Classifier: Programming Language :: Python :: 3
Classifier: Programming Language :: Python :: 3.8
Classifier: Programming Language :: Python :: 3.9
Classifier: Programming Language :: Python :: 3.10
Classifier: Programming Language :: Python :: 3.11
Classifier: Programming Language :: Python :: 3.12
